LICENSE
MANIFEST.in
README
setup.cfg
setup.py
doc/_build/html/.buildinfo
doc/_build/html/extract.html
doc/_build/html/genindex.html
doc/_build/html/index.html
doc/_build/html/modules.html
doc/_build/html/objects.inv
doc/_build/html/py-modindex.html
doc/_build/html/search.html
doc/_build/html/searchindex.js
doc/_build/html/setup.html
doc/_build/html/test.html
doc/_build/html/webcrawler.html
doc/_build/html/.eggs/pytest_runner-4.2-py2.7.egg/EGG-INFO/DESCRIPTION.html
doc/_build/html/_modules/extract.html
doc/_build/html/_modules/index.html
doc/_build/html/_modules/test/test_analyze.html
doc/_build/html/_modules/test/test_crawler.html
doc/_build/html/_modules/webcrawler/analyze.html
doc/_build/html/_modules/webcrawler/crawler.html
doc/_build/html/_modules/webcrawler/extract.html
doc/_build/html/_sources/extract.rst.txt
doc/_build/html/_sources/index.rst.txt
doc/_build/html/_sources/modules.rst.txt
doc/_build/html/_sources/setup.rst.txt
doc/_build/html/_sources/test.rst.txt
doc/_build/html/_sources/webcrawler.rst.txt
doc/_build/html/_sources/.eggs/pytest_runner-4.2-py2.7.egg/EGG-INFO/DESCRIPTION.rst.txt
doc/_build/html/_static/ajax-loader.gif
doc/_build/html/_static/basic.css
doc/_build/html/_static/classic.css
doc/_build/html/_static/comment-bright.png
doc/_build/html/_static/comment-close.png
doc/_build/html/_static/comment.png
doc/_build/html/_static/doctools.js
doc/_build/html/_static/documentation_options.js
doc/_build/html/_static/down-pressed.png
doc/_build/html/_static/down.png
doc/_build/html/_static/file.png
doc/_build/html/_static/jquery-3.2.1.js
doc/_build/html/_static/jquery.js
doc/_build/html/_static/minus.png
doc/_build/html/_static/plus.png
doc/_build/html/_static/pygments.css
doc/_build/html/_static/searchtools.js
doc/_build/html/_static/sidebar.js
doc/_build/html/_static/underscore-1.3.1.js
doc/_build/html/_static/underscore.js
doc/_build/html/_static/up-pressed.png
doc/_build/html/_static/up.png
doc/_build/html/_static/websupport.js
src/extract
src/Final_Project.egg-info/PKG-INFO
src/Final_Project.egg-info/SOURCES.txt
src/Final_Project.egg-info/dependency_links.txt
src/Final_Project.egg-info/top_level.txt
src/webcrawler/__init__.py
src/webcrawler/analyze.py
src/webcrawler/crawler.py
src/webcrawler/extract.py
src/webcrawler/other/ratio.png
