Metadata-Version: 1.1
Name: Final-Project
Version: 1.0
Summary: Extracting home information from zillow.com
Home-page: http://dislbenn.github.io
Author: Disaiah Benentt
Author-email: dlbennett365@students.ecsu.edu
License: Creative Commons Attribution-Noncommercial-Share Alike license
Platform: UNKNOWN
Classifier: Development Status :: 4 - Beta
Classifier: Environment :: X11 Applications :: GTK
Classifier: Intended Audience :: End Users/Desktop
Classifier: Intended Audience :: Developers
Classifier: License :: OSI Approved :: GNU General Public License (GPL)
Classifier: Operating System :: POSIX :: Linux
Classifier: Programming Language :: Python
Classifier: Topic :: Desktop Environment
Classifier: Topic :: Text Processing :: Fonts
